mineapy/__init__.py
mineapy/core/__init__.py
mineapy/core/enumTask.py
mineapy/core/logger.py
mineapy/core/mhygepdf.py
mineapy/core/numerics.py
mineapy/core/rxnExp.py
mineapy/core/taskEnrich.py
mineapy/core/thermo_model.py
mineapy/core/utils.py
mineapy/optim/__init__.py
mineapy/optim/constraints.py
mineapy/optim/variables.py
mineapy-0.0.4.dist-info/LICENSE
mineapy-0.0.4.dist-info/METADATA
mineapy-0.0.4.dist-info/WHEEL
mineapy-0.0.4.dist-info/top_level.txt
mineapy-0.0.4.dist-info/RECORD
